aiologto/__init__.py
aiologto/client.py
aiologto/routes.py
aiologto/version.py
aiologto/schemas/__init__.py
aiologto/schemas/oidc.py
aiologto/schemas/users.py
aiologto/types/__init__.py
aiologto/types/base.py
aiologto/types/errors.py
aiologto/types/oidc.py
aiologto/utils/__init__.py
aiologto/utils/caching.py
aiologto/utils/config.py
aiologto/utils/helpers.py
aiologto/utils/logs.py
aiologto-0.0.6.dist-info/LICENSE
aiologto-0.0.6.dist-info/METADATA
aiologto-0.0.6.dist-info/WHEEL
aiologto-0.0.6.dist-info/top_level.txt
aiologto-0.0.6.dist-info/RECORD
