Metadata-Version: 2.1
Name: aiologto
Version: 0.0.6
Summary: Unofficial Asyncronous Python Client for Logto
Home-page: https://github.com/GrowthEngineAI/aiologto
Author: Tri Songz
Author-email: ts@growthengineai.com
License: MIT License
Classifier: Intended Audience :: Developers
Classifier: License :: OSI Approved :: MIT License
Classifier: Programming Language :: Python :: 3.7
Classifier: Topic :: Software Development :: Libraries
License-File: LICENSE
Requires-Dist: aiohttpx
Requires-Dist: backoff
Requires-Dist: python-jose
Requires-Dist: aiokeydb
